[{"id":"article_103","type":"article","title":"Frequently Asked Questions- 2011 Census Unrounded Population and Household Estimates for Wales","summary":"","metaDescription":"We answer some frequently asked questions from the first release of unrounded results from the 2011 Census. This release provides information about the usually resident population of Wales, including age, sex, the number of households and the number of short-term residents.","contactEmail":"census.customerservices @ons.gsi.gov.uk","contactName":"Garnett Compton","contactTelephone":"+44 (0)1329 444972","start-date":"","end-date":""}]
